twb/__init__.py
twb/builder.py
twb/builder_helpers.py
twb/decompressor.py
twb/logger.py
twb/logger_init.py
twb/modifier.py
twb/parallelization.py
twb/reader.py
twb/utils.py
twb/warehouse.py
twb_project-1.1.2.dist-info/LICENSE
twb_project-1.1.2.dist-info/METADATA
twb_project-1.1.2.dist-info/WHEEL
twb_project-1.1.2.dist-info/entry_points.txt
twb_project-1.1.2.dist-info/RECORD
