Metadata-Version: 2.1
Name: twb-project
Version: 1.1.2
Summary: An unified tool for the research in extracting information from Wikipedia Edit History chunk.
Home-page: https://twb.lingxi.li/
License: GNU GPL
Author: Lingxi Li
Author-email: hi@lingxi.li
Requires-Python: >=3.8,<4
Classifier: License :: Other/Proprietary License
Classifier: Programming Language :: Python :: 3
Classifier: Programming Language :: Python :: 3.8
Classifier: Programming Language :: Python :: 3.9
Classifier: Programming Language :: Python :: 3.10
Classifier: Programming Language :: Python :: 3.11
Requires-Dist: beautifulsoup4 (>=4.12.2,<5.0.0)
Requires-Dist: jsonlines (>=3.1.0,<4.0.0)
Requires-Dist: psutil (>=5.9.5,<6.0.0)
Requires-Dist: py7zr (>=0.20.5,<0.21.0)
Requires-Dist: requests (>=2.31.0,<3.0.0)
Requires-Dist: tqdm (>=4.65.0,<5.0.0)
Requires-Dist: xmltodict (>=0.13.0,<0.14.0)
Requires-Dist: zstandard (>=0.21.0,<0.22.0)
Project-URL: Repository, https://github.com/lilingxi01/twb-project
